{
    "aa": {
        "https://careers.blizzard.com": {
            "used": 8, 
            "word": 1
        }
    }, 
    "ab": {
        "https://careers.blizzard.com": {
            "used": 8, 
            "word": 240
        }
    }, 
    "abd": {
        "https://careers.blizzard.com": {
            "used": 8, 
            "word": 1
        }
    }, 
    "abeee": {
        "https://careers.blizzard.com": {
            "used": 8, 
            "word": 3
        }
    }, 
    "abilites": {
        "https://overwatchleague.com/en-us": {
            "used": 29, 
            "word": 1
        }
    }, 
    "abilities": {
        "https://playoverwatch.com": {
            "used": 38, 
            "word": 1
        }, 
        "https://playoverwatch.com/en-us": {
            "used": 0, 
            "word": 1
        }, 
        "https://us.battle.net/d3": {
            "used": 27, 
            "word": 1
        }, 
        "https://us.battle.net/heroes": {
            "used": 12, 
            "word": 2
        }
    }, 
    "ability": {
        "http://us.blizzard.com/company/about/privacy.html": {
            "used": 24, 
            "word": 1
        }
    }, 
    "abused": {
        "http://us.blizzard.com/company/about/privacy.html": {
            "used": 24, 
            "word": 1
        }
    }, 
    "ac": {
        "https://careers.blizzard.com": {
            "used": 8, 
            "word": 224
        }, 
        "https://www.youtube.com/PlayOverwatch": {
            "used": 5, 
            "word": 8
        }, 
        "https://www.youtube.com/watch": {
            "used": 12, 
            "word": 9
        }
    }, 
    "aca": {
        "https://careers.blizzard.com": {
            "used": 8, 
            "word": 6
        }
    }, 
    "acbe": {
        "https://careers.blizzard.com": {
            "used": 8, 
            "word": 1
        }
    }, 
    "accent": {
        "https://careers.blizzard.com": {
            "used": 8, 
            "word": 1
        }
    }, 
    "accept": {
        "https://careers.blizzard.com": {
            "used": 9, 
            "word": 1
        }
    }, 
    "acceptance": {
        "http://us.blizzard.com/company/about/privacy.html": {
            "used": 24, 
            "word": 1
        }
    }, 
    "accepted": {
        "http://us.blizzard.com/company/about/privacy.html": {
            "used": 24, 
            "word": 1
        }
    }, 
    "access": {
        "http://us.blizzard.com/company/about/privacy.html": {
            "used": 24, 
            "word": 4
        }, 
        "https://dev.battle.net": {
            "used": 4, 
            "word": 1
        }, 
        "https://www.twitter.com/PlayOverwatch": {
            "used": 5, 
            "word": 1
        }
    }, 
    "accompanied": {
        "http://blizz.ly/OWC2017": {
            "used": 2, 
            "word": 1
        }, 
        "https://playoverwatch.com/en-us/worldcup": {
            "used": 23, 
            "word": 1
        }
    }, 
    "accomplish": {
        "https://www.youtube.com/PlayOverwatch": {
            "used": 5, 
            "word": 1
        }
    }, 
    "accordance": {
        "http://us.blizzard.com/company/about/privacy.html": {
            "used": 24, 
            "word": 2
        }
    }, 
    "account": {
        "http://blizz.ly/OWC2017": {
            "used": 2, 
            "word": 10
        }, 
        "http://blizz.ly/OWU2017": {
            "used": 2, 
            "word": 7
        }, 
        "http://us.blizzard.com/company/about/privacy.html": {
            "used": 24, 
            "word": 11
        }, 
        "https://battle.net/shop": {
            "used": 29, 
            "word": 9
        }, 
        "https://careers.blizzard.com": {
            "used": 9, 
            "word": 8
        }, 
        "https://dev.battle.net": {
            "used": 4, 
            "word": 4
        }, 
        "https://overwatchleague.com/en-us": {
            "used": 29, 
            "word": 3
        }, 
        "https://playoverwatch.com": {
            "used": 38, 
            "word": 9
        }, 
        "https://playoverwatch.com/en-us": {
            "used": 0, 
            "word": 9
        }, 
        "https://playoverwatch.com/en-us/worldcup": {
            "used": 23, 
            "word": 10
        }, 
        "https://us.battle.net/account": {
            "used": 40, 
            "word": 2
        }, 
        "https://us.battle.net/account/download": {
            "used": 12, 
            "word": 8
        }, 
        "https://us.battle.net/d3": {
            "used": 27, 
            "word": 4
        }, 
        "https://us.battle.net/feedback": {
            "used": 10, 
            "word": 5
        }, 
        "https://us.battle.net/forums": {
            "used": 18, 
            "word": 3
        }, 
        "https://us.battle.net/games/classic": {
            "used": 18, 
            "word": 11
        }, 
        "https://us.battle.net/hearthstone": {
            "used": 27, 
            "word": 7
        }, 
        "https://us.battle.net/hearthstone/en-us/esports": {
            "used": 16, 
            "word": 7
        }, 
        "https://us.battle.net/heroes": {
            "used": 12, 
            "word": 7
        }, 
        "https://us.battle.net/sc2": {
            "used": 27, 
            "word": 2
        }, 
        "https://us.battle.net/support": {
            "used": 37, 
            "word": 11
        }, 
        "https://us.heroesofthestorm.com/esports/en-us": {
            "used": 25, 
            "word": 7
        }, 
        "https://www.twitter.com/PlayOverwatch": {
            "used": 5, 
            "word": 29
        }
    }, 
    "accountprotected": {
        "https://www.twitter.com/PlayOverwatch": {
            "used": 5, 
            "word": 9
        }
    }, 
    "accounts": {
        "https://dev.battle.net": {
            "used": 4, 
            "word": 1
        }, 
        "https://us.battle.net/account/download": {
            "used": 12, 
            "word": 1
        }, 
        "https://us.battle.net/games/classic": {
            "used": 18, 
            "word": 2
        }, 
        "https://www.twitter.com/PlayOverwatch": {
            "used": 5, 
            "word": 1
        }
    }, 
    "acd": {
        "https://careers.blizzard.com": {
            "used": 8, 
            "word": 1
        }
    }, 
    "achieve": {
        "https://playoverwatch.com": {
            "used": 38, 
            "word": 1
        }, 
        "https://playoverwatch.com/en-us": {
            "used": 0, 
            "word": 1
        }
    }, 
    "acode": {
        "https://battle.net/shop": {
            "used": 29, 
            "word": 1
        }
    }, 
    "acquisition": {
        "http://us.blizzard.com/company/about/privacy.html": {
            "used": 24, 
            "word": 1
        }
    }, 
    "acting": {
        "http://us.blizzard.com/company/about/privacy.html": {
            "used": 24, 
            "word": 3
        }
    }, 
    "action": {
        "http://blizz.ly/OWU2017": {
            "used": 2, 
            "word": 2
        }, 
        "http://us.blizzard.com/company/about/privacy.html": {
            "used": 24, 
            "word": 3
        }, 
        "https://careers.blizzard.com": {
            "used": 8, 
            "word": 7
        }, 
        "https://overwatchleague.com/en-us": {
            "used": 29, 
            "word": 3
        }, 
        "https://us.battle.net/sc2": {
            "used": 27, 
            "word": 2
        }, 
        "https://us.heroesofthestorm.com/esports/en-us": {
            "used": 13, 
            "word": 11
        }, 
        "https://www.youtube.com/PlayOverwatch": {
            "used": 5, 
            "word": 1
        }
    }, 
    "actions": {
        "https://us.heroesofthestorm.com/esports/en-us": {
            "used": 13, 
            "word": 4
        }
    }, 
    "activate": {
        "https://careers.blizzard.com": {
            "used": 8, 
            "word": 1
        }
    }, 
    "active": {
        "https://careers.blizzard.com": {
            "used": 8, 
            "word": 1
        }, 
        "https://us.heroesofthestorm.com/esports/en-us": {
            "used": 13, 
            "word": 84
        }
    }, 
    "activision": {
        "https://careers.blizzard.com": {
            "used": 8, 
            "word": 1
        }
    }, 
    "activities": {
        "http://us.blizzard.com/company/about/privacy.html": {
            "used": 24, 
            "word": 8
        }
    }, 
    "activity": {
        "http://us.blizzard.com/company/about/privacy.html": {
            "used": 24, 
            "word": 1
        }, 
        "https://us.battle.net/support": {
            "used": 37, 
            "word": 2
        }
    }, 
    "ad": {
        "http://us.blizzard.com/company/about/privacy.html": {
            "used": 24, 
            "word": 66
        }, 
        "https://careers.blizzard.com": {
            "used": 8, 
            "word": 75
        }
    }, 
    "ada": {
        "https://careers.blizzard.com": {
            "used": 8, 
            "word": 19
        }
    }, 
    "adapt": {
        "http://us.blizzard.com/company/about/privacy.html": {
            "used": 24, 
            "word": 1
        }
    }, 
    "adaptive": {
        "https://careers.blizzard.com": {
            "used": 8, 
            "word": 18
        }
    }, 
    "adaptivesm": {
        "https://careers.blizzard.com": {
            "used": 8, 
            "word": 1
        }
    }, 
    "adc": {
        "https://careers.blizzard.com": {
            "used": 8, 
            "word": 1
        }
    }, 
    "add": {
        "https://us.battle.net/account/download": {
            "used": 12, 
            "word": 3
        }, 
        "https://www.twitter.com/PlayOverwatch": {
            "used": 5, 
            "word": 6
        }
    }, 
    "addition": {
        "http://us.blizzard.com/company/about/privacy.html": {
            "used": 24, 
            "word": 11
        }
    }, 
    "additional": {
        "http://us.blizzard.com/company/about/privacy.html": {
            "used": 24, 
            "word": 6
        }, 
        "https://us.battle.net/hearthstone": {
            "used": 27, 
            "word": 1
        }
    }, 
    "address": {
        "http://us.blizzard.com/company/about/privacy.html": {
            "used": 24, 
            "word": 15
        }, 
        "https://us.battle.net/account/download": {
            "used": 12, 
            "word": 2
        }
    }, 
    "addressed": {
        "http://us.blizzard.com/company/about/privacy.html": {
            "used": 24, 
            "word": 2
        }, 
        "https://www.twitter.com/PlayOverwatch": {
            "used": 5, 
            "word": 1
        }
    }, 
    "addresses": {
        "http://us.blizzard.com/company/about/privacy.html": {
            "used": 24, 
            "word": 4
        }, 
        "https://us.battle.net/account/download": {
            "used": 12, 
            "word": 1
        }
    }, 
    "adept": {
        "https://us.battle.net/sc2": {
            "used": 27, 
            "word": 1
        }
    }, 
    "adhere": {
        "http://us.blizzard.com/company/about/privacy.html": {
            "used": 24, 
            "word": 2
        }
    }, 
    "administering": {
        "http://us.blizzard.com/company/about/privacy.html": {
            "used": 24, 
            "word": 1
        }
    }, 
    "administration": {
        "http://us.blizzard.com/company/about/privacy.html": {
            "used": 24, 
            "word": 1
        }, 
        "https://careers.blizzard.com": {
            "used": 9, 
            "word": 1
        }
    }, 
    "adopted": {
        "http://us.blizzard.com/company/about/privacy.html": {
            "used": 24, 
            "word": 1
        }
    }, 
    "adoption": {
        "http://blizzard.com": {
            "used": 34, 
            "word": 1
        }
    }, 
    "ads": {
        "http://us.blizzard.com/company/about/privacy.html": {
            "used": 24, 
            "word": 3
        }, 
        "https://www.twitter.com/PlayOverwatch": {
            "used": 5, 
            "word": 1
        }
    }, 
    "advance": {
        "http://blizz.ly/OWC2017": {
            "used": 2, 
            "word": 1
        }, 
        "https://playoverwatch.com/en-us/worldcup": {
            "used": 23, 
            "word": 1
        }
    }, 
    "adventurers": {
        "https://overwatchleague.com/en-us": {
            "used": 29, 
            "word": 1
        }, 
        "https://playoverwatch.com": {
            "used": 38, 
            "word": 1
        }, 
        "https://playoverwatch.com/en-us": {
            "used": 0, 
            "word": 1
        }
    }, 
    "advertiser": {
        "http://us.blizzard.com/company/about/privacy.html": {
            "used": 24, 
            "word": 4
        }
    }, 
    "advertisers": {
        "http://us.blizzard.com/company/about/privacy.html": {
            "used": 24, 
            "word": 3
        }
    }, 
    "advertising": {
        "http://us.blizzard.com/company/about/privacy.html": {
            "used": 24, 
            "word": 8
        }
    }, 
    "advised": {
        "http://us.blizzard.com/company/about/privacy.html": {
            "used": 24, 
            "word": 2
        }
    }, 
    "aeit": {
        "https://us.heroesofthestorm.com/esports/en-us": {
            "used": 13, 
            "word": 2
        }
    }, 
    "aesthetics": {
        "https://www.twitter.com/PlayOverwatch": {
            "used": 5, 
            "word": 1
        }
    }, 
    "af": {
        "https://careers.blizzard.com": {
            "used": 8, 
            "word": 22
        }
    }, 
    "affiliate": {
        "http://us.blizzard.com/company/about/privacy.html": {
            "used": 24, 
            "word": 4
        }
    }, 
    "affiliates": {
        "http://us.blizzard.com/company/about/privacy.html": {
            "used": 24, 
            "word": 2
        }
    }, 
    "afford": {
        "https://overwatchleague.com/en-us": {
            "used": 29, 
            "word": 1
        }, 
        "https://www.facebook.com/PlayOverwatch": {
            "used": 3, 
            "word": 1
        }
    }, 
    "afreeca": {
        "http://blizz.ly/OWC2017": {
            "used": 2, 
            "word": 1
        }, 
        "https://playoverwatch.com/en-us/worldcup": {
            "used": 23, 
            "word": 1
        }
    }, 
    "age": {
        "http://us.blizzard.com/company/about/privacy.html": {
            "used": 24, 
            "word": 25
        }
    }, 
    "agencies": {
        "https://careers.blizzard.com": {
            "used": 9, 
            "word": 1
        }
    }, 
    "agent": {
        "https://www.youtube.com/PlayOverwatch": {
            "used": 5, 
            "word": 3
        }
    }, 
    "agents": {
        "http://blizz.ly/OWU2017": {
            "used": 2, 
            "word": 2
        }, 
        "https://www.facebook.com/PlayOverwatch": {
            "used": 8, 
            "word": 1
        }, 
        "https://www.twitter.com/PlayOverwatch": {
            "used": 5, 
            "word": 1
        }, 
        "https://www.youtube.com/PlayOverwatch": {
            "used": 5, 
            "word": 2
        }
    }, 
    "agentsincluding": {
        "http://blizz.ly/OWU2017": {
            "used": 2, 
            "word": 1
        }
    }, 
    "aggregate": {
        "http://us.blizzard.com/company/about/privacy.html": {
            "used": 24, 
            "word": 4
        }
    }, 
    "ago": {
        "https://us.battle.net/hearthstone": {
            "used": 27, 
            "word": 2
        }, 
        "https://us.battle.net/heroes": {
            "used": 12, 
            "word": 1
        }, 
        "https://us.battle.net/sc2": {
            "used": 27, 
            "word": 3
        }, 
        "https://www.twitter.com/PlayOverwatch": {
            "used": 5, 
            "word": 1
        }
    }, 
    "agree": {
        "http://us.blizzard.com/company/about/privacy.html": {
            "used": 24, 
            "word": 5
        }
    }, 
    "agreed": {
        "https://careers.blizzard.com": {
            "used": 9, 
            "word": 1
        }
    }, 
    "agreement": {
        "http://us.blizzard.com/company/about/privacy.html": {
            "used": 24, 
            "word": 3
        }, 
        "https://www.twitter.com/PlayOverwatch": {
            "used": 5, 
            "word": 1
        }
    }, 
    "agreements": {
        "http://us.blizzard.com/company/about/privacy.html": {
            "used": 24, 
            "word": 2
        }
    }, 
    "ahead": {
        "https://overwatchleague.com/en-us": {
            "used": 29, 
            "word": 1
        }
    }, 
    "ai": {
        "https://us.battle.net/hearthstone": {
            "used": 27, 
            "word": 13
        }
    }, 
    "aid": {
        "https://us.heroesofthestorm.com/esports/en-us": {
            "used": 13, 
            "word": 2
        }
    }, 
    "ain": {
        "https://www.twitter.com/PlayOverwatch": {
            "used": 5, 
            "word": 5
        }, 
        "https://www.youtube.com/watch": {
            "used": 12, 
            "word": 4
        }
    }, 
    "air": {
        "https://wcs.starcraft2.com/en-us": {
            "used": 17, 
            "word": 2
        }
    }, 
    "airtel": {
        "https://www.twitter.com/PlayOverwatch": {
            "used": 5, 
            "word": 1
        }
    }, 
    "ais": {
        "https://us.heroesofthestorm.com/esports/en-us": {
            "used": 13, 
            "word": 8
        }
    }, 
    "aj": {
        "https://us.heroesofthestorm.com/esports/en-us": {
            "used": 13, 
            "word": 6
        }
    }, 
    "ajrig": {
        "https://us.heroesofthestorm.com/esports/en-us": {
            "used": 13, 
            "word": 3
        }
    }, 
    "akamaihd": {
        "https://careers.blizzard.com": {
            "used": 8, 
            "word": 10
        }, 
        "https://us.heroesofthestorm.com/esports/en-us": {
            "used": 13, 
            "word": 85
        }
    }, 
    "akamaized": {
        "https://careers.blizzard.com": {
            "used": 8, 
            "word": 9
        }
    }, 
    "alanfilmz": {
        "https://www.youtube.com/watch": {
            "used": 12, 
            "word": 1
        }
    }, 
    "alarak": {
        "https://us.heroesofthestorm.com/esports/en-us": {
            "used": 13, 
            "word": 1
        }
    }, 
    "alejandro": {
        "https://www.facebook.com/PlayOverwatch": {
            "used": 8, 
            "word": 1
        }
    }, 
    "align": {
        "https://careers.blizzard.com": {
            "used": 8, 
            "word": 12
        }
    }, 
    "alive": {
        "https://www.youtube.com/PlayOverwatch": {
            "used": 5, 
            "word": 3
        }
    }, 
    "alliance": {
        "http://us.blizzard.com/company/about/privacy.html": {
            "used": 24, 
            "word": 1
        }
    }, 
    "allows": {
        "http://us.blizzard.com/company/about/privacy.html": {
            "used": 24, 
            "word": 3
        }
    }, 
    "already": {
        "https://us.battle.net/games/classic": {
            "used": 18, 
            "word": 1
        }, 
        "https://www.facebook.com/PlayOverwatch": {
            "used": 8, 
            "word": 3
        }
    }, 
    "alt": {
        "https://careers.blizzard.com": {
            "used": 8, 
            "word": 16
        }, 
        "https://us.heroesofthestorm.com/esports/en-us": {
            "used": 13, 
            "word": 73
        }
    }, 
    "alteration": {
        "http://us.blizzard.com/company/about/privacy.html": {
            "used": 24, 
            "word": 1
        }
    }, 
    "always": {
        "http://blizz.ly/OWU2017": {
            "used": 2, 
            "word": 1
        }, 
        "https://dev.battle.net": {
            "used": 4, 
            "word": 1
        }, 
        "https://us.heroesofthestorm.com/esports/en-us": {
            "used": 25, 
            "word": 5
        }, 
        "https://www.twitter.com/PlayOverwatch": {
            "used": 5, 
            "word": 1
        }
    }, 
    "americas": {
        "http://blizz.ly/OWC2017": {
            "used": 2, 
            "word": 4
        }, 
        "http://blizz.ly/OWU2017": {
            "used": 2, 
            "word": 1
        }, 
        "http://blizzard.com": {
            "used": 34, 
            "word": 1
        }, 
        "http://us.blizzard.com/company/about/privacy.html": {
            "used": 24, 
            "word": 1
        }, 
        "https://battle.net/shop": {
            "used": 29, 
            "word": 1
        }, 
        "https://overwatchleague.com/en-us": {
            "used": 29, 
            "word": 4
        }, 
        "https://playoverwatch.com": {
            "used": 38, 
            "word": 1
        }, 
        "https://playoverwatch.com/en-us": {
            "used": 0, 
            "word": 1
        }, 
        "https://playoverwatch.com/en-us/worldcup": {
            "used": 23, 
            "word": 4
        }, 
        "https://us.battle.net/account/download": {
            "used": 12, 
            "word": 4
        }, 
        "https://us.battle.net/d3": {
            "used": 27, 
            "word": 2
        }, 
        "https://us.battle.net/feedback": {
            "used": 10, 
            "word": 1
        }, 
        "https://us.battle.net/forums": {
            "used": 18, 
            "word": 4
        }, 
        "https://us.battle.net/games/classic": {
            "used": 18, 
            "word": 1
        }, 
        "https://us.battle.net/hearthstone": {
            "used": 27, 
            "word": 4
        }, 
        "https://us.battle.net/hearthstone/en-us/esports": {
            "used": 16, 
            "word": 5
        }, 
        "https://us.battle.net/heroes": {
            "used": 12, 
            "word": 4
        }, 
        "https://us.battle.net/sc2": {
            "used": 27, 
            "word": 2
        }, 
        "https://us.battle.net/support": {
            "used": 37, 
            "word": 1
        }, 
        "https://us.heroesofthestorm.com/esports/en-us": {
            "used": 25, 
            "word": 4
        }, 
        "https://wcs.starcraft2.com/en-us": {
            "used": 17, 
            "word": 4
        }
    }, 
    "amon": {
        "https://us.battle.net/sc2": {
            "used": 27, 
            "word": 3
        }
    }, 
    "amons": {
        "https://us.battle.net/sc2": {
            "used": 27, 
            "word": 1
        }
    }, 
    "amp": {
        "http://blizz.ly/OWU2017": {
            "used": 2, 
            "word": 5
        }, 
        "http://blizzard.com": {
            "used": 34, 
            "word": 1
        }, 
        "http://us.blizzard.com/company/about/privacy.html": {
            "used": 24, 
            "word": 5
        }, 
        "https://battle.net/shop": {
            "used": 29, 
            "word": 5
        }, 
        "https://blizzard.gamespress.com": {
            "used": 4, 
            "word": 3
        }, 
        "https://careers.blizzard.com": {
            "used": 8, 
            "word": 5
        }, 
        "https://dev.battle.net": {
            "used": 4, 
            "word": 1
        }, 
        "https://playoverwatch.com": {
            "used": 38, 
            "word": 5
        }, 
        "https://playoverwatch.com/en-us": {
            "used": 0, 
            "word": 5
        }, 
        "https://us.battle.net/account/download": {
            "used": 12, 
            "word": 10
        }, 
        "https://us.battle.net/d3": {
            "used": 27, 
            "word": 4
        }, 
        "https://us.battle.net/feedback": {
            "used": 10, 
            "word": 5
        }, 
        "https://us.battle.net/games/classic": {
            "used": 18, 
            "word": 5
        }, 
        "https://us.battle.net/support": {
            "used": 37, 
            "word": 6
        }, 
        "https://us.heroesofthestorm.com/esports/en-us": {
            "used": 13, 
            "word": 41
        }, 
        "https://worldofwarcraft.com": {
            "used": 44, 
            "word": 6
        }, 
        "https://www.twitter.com/PlayOverwatch": {
            "used": 5, 
            "word": 2
        }, 
        "https://www.youtube.com/watch": {
            "used": 12, 
            "word": 5
        }
    }, 
    "ana": {
        "https://playoverwatch.com": {
            "used": 38, 
            "word": 2
        }, 
        "https://playoverwatch.com/en-us": {
            "used": 0, 
            "word": 2
        }
    }, 
    "anaheim": {
        "http://blizzard.com": {
            "used": 34, 
            "word": 2
        }
    }, 
    "analytics": {
        "http://us.blizzard.com/company/about/privacy.html": {
            "used": 24, 
            "word": 2
        }, 
        "https://careers.blizzard.com": {
            "used": 8, 
            "word": 82
        }, 
        "https://us.heroesofthestorm.com/esports/en-us": {
            "used": 13, 
            "word": 100
        }
    }, 
    "analyzing": {
        "http://us.blizzard.com/company/about/privacy.html": {
            "used": 24, 
            "word": 1
        }
    }, 
    "anchor": {
        "https://careers.blizzard.com": {
            "used": 8, 
            "word": 9
        }
    }, 
    "and": {
        "http://blizz.ly/OWC2017": {
            "used": 2, 
            "word": 15
        }, 
        "http://blizz.ly/OWU2017": {
            "used": 2, 
            "word": 8
        }, 
        "http://blizzard.com": {
            "used": 34, 
            "word": 8
        }, 
        "http://us.blizzard.com/company/about/privacy.html": {
            "used": 24, 
            "word": 110
        }, 
        "https://battle.net/shop": {
            "used": 29, 
            "word": 1
        }, 
        "https://blizzard.gamespress.com": {
            "used": 4, 
            "word": 31
        }, 
        "https://careers.blizzard.com": {
            "used": 9, 
            "word": 7
        }, 
        "https://dev.battle.net": {
            "used": 4, 
            "word": 6
        }, 
        "https://overwatchleague.com/en-us": {
            "used": 29, 
            "word": 13
        }, 
        "https://playoverwatch.com": {
            "used": 38, 
            "word": 17
        }, 
        "https://playoverwatch.com/en-us": {
            "used": 0, 
            "word": 17
        }, 
        "https://playoverwatch.com/en-us/worldcup": {
            "used": 23, 
            "word": 15
        }, 
        "https://us.battle.net/account/download": {
            "used": 12, 
            "word": 1
        }, 
        "https://us.battle.net/d3": {
            "used": 27, 
            "word": 10
        }, 
        "https://us.battle.net/games/classic": {
            "used": 18, 
            "word": 6
        }, 
        "https://us.battle.net/hearthstone": {
            "used": 27, 
            "word": 11
        }, 
        "https://us.battle.net/hearthstone/en-us/esports": {
            "used": 16, 
            "word": 6
        }, 
        "https://us.battle.net/heroes": {
            "used": 12, 
            "word": 4
        }, 
        "https://us.battle.net/sc2": {
            "used": 27, 
            "word": 13
        }, 
        "https://us.heroesofthestorm.com/esports/en-us": {
            "used": 25, 
            "word": 23
        }, 
        "https://wcs.starcraft2.com/en-us": {
            "used": 17, 
            "word": 4
        }, 
        "https://worldofwarcraft.com": {
            "used": 44, 
            "word": 1
        }, 
        "https://www.facebook.com/PlayOverwatch": {
            "used": 8, 
            "word": 13
        }, 
        "https://www.twitter.com/PlayOverwatch": {
            "used": 5, 
            "word": 12
        }, 
        "https://www.youtube.com/PlayOverwatch": {
            "used": 5, 
            "word": 12
        }
    }, 
    "angel": {
        "https://www.youtube.com/watch": {
            "used": 12, 
            "word": 1
        }
    }, 
    "animated": {
        "https://www.youtube.com/PlayOverwatch": {
            "used": 5, 
            "word": 13
        }
    }, 
    "animatedopacity": {
        "https://us.heroesofthestorm.com/esports/en-us": {
            "used": 13, 
            "word": 3
        }
    }, 
    "anniversary": {
        "http://us.blizzard.com/company/about/privacy.html": {
            "used": 24, 
            "word": 1
        }, 
        "https://blizzard.gamespress.com": {
            "used": 4, 
            "word": 1
        }
    }, 
    "announce": {
        "http://blizz.ly/OWC2017": {
            "used": 2, 
            "word": 2
        }, 
        "https://playoverwatch.com/en-us/worldcup": {
            "used": 23, 
            "word": 2
        }
    }, 
    "announced": {
        "http://blizzard.com": {
            "used": 34, 
            "word": 1
        }
    }, 
    "announcement": {
        "https://blizzard.gamespress.com": {
            "used": 4, 
            "word": 4
        }, 
        "https://overwatchleague.com/en-us": {
            "used": 29, 
            "word": 1
        }
    }, 
    "announcer": {
        "https://battle.net/shop": {
            "used": 29, 
            "word": 1
        }, 
        "https://us.battle.net/sc2": {
            "used": 27, 
            "word": 1
        }
    }, 
    "announces": {
        "https://blizzard.gamespress.com": {
            "used": 4, 
            "word": 1
        }
    }, 
    "announcing": {
        "https://us.battle.net/heroes": {
            "used": 12, 
            "word": 1
        }
    }, 
    "anonymous": {
        "http://us.blizzard.com/company/about/privacy.html": {
            "used": 24, 
            "word": 1
        }
    }, 
    "answered": {
        "https://overwatchleague.com/en-us": {
            "used": 29, 
            "word": 1
        }
    }, 
    "answers": {
        "https://us.battle.net/d3": {
            "used": 27, 
            "word": 2
        }
    }, 
    "ant": {
        "https://www.facebook.com/PlayOverwatch": {
            "used": 8, 
            "word": 2
        }
    }, 
    "anthology": {
        "https://us.battle.net/account/download": {
            "used": 12, 
            "word": 2
        }
    }, 
    "antics": {
        "https://us.heroesofthestorm.com/esports/en-us": {
            "used": 13, 
            "word": 2
        }
    }, 
    "antihero": {
        "https://www.youtube.com/watch": {
            "used": 12, 
            "word": 1
        }
    }, 
    "anz": {
        "https://wcs.starcraft2.com/en-us": {
            "used": 17, 
            "word": 1
        }
    }, 
    "aopa": {
        "https://us.heroesofthestorm.com/esports/en-us": {
            "used": 13, 
            "word": 5
        }
    }, 
    "api": {
        "http://blizz.ly/OWC2017": {
            "used": 2, 
            "word": 2
        }, 
        "http://blizz.ly/OWU2017": {
            "used": 2, 
            "word": 1
        }, 
        "https://battle.net/shop": {
            "used": 29, 
            "word": 1
        }, 
        "https://careers.blizzard.com": {
            "used": 9, 
            "word": 1
        }, 
        "https://dev.battle.net": {
            "used": 4, 
            "word": 6
        }, 
        "https://overwatchleague.com/en-us": {
            "used": 29, 
            "word": 2
        }, 
        "https://playoverwatch.com": {
            "used": 38, 
            "word": 1
        }, 
        "https://playoverwatch.com/en-us": {
            "used": 0, 
            "word": 1
        }, 
        "https://playoverwatch.com/en-us/worldcup": {
            "used": 23, 
            "word": 2
        }, 
        "https://us.battle.net/account/download": {
            "used": 12, 
            "word": 1
        }, 
        "https://us.battle.net/d3": {
            "used": 27, 
            "word": 1
        }, 
        "https://us.battle.net/feedback": {
            "used": 10, 
            "word": 1
        }, 
        "https://us.battle.net/forums": {
            "used": 18, 
            "word": 2
        }, 
        "https://us.battle.net/games/classic": {
            "used": 18, 
            "word": 1
        }, 
        "https://us.battle.net/hearthstone": {
            "used": 27, 
            "word": 2
        }, 
        "https://us.battle.net/hearthstone/en-us/esports": {
            "used": 16, 
            "word": 2
        }, 
        "https://us.battle.net/heroes": {
            "used": 12, 
            "word": 2
        }, 
        "https://us.battle.net/sc2": {
            "used": 27, 
            "word": 1
        }, 
        "https://us.battle.net/support": {
            "used": 37, 
            "word": 1
        }, 
        "https://us.heroesofthestorm.com/esports/en-us": {
            "used": 25, 
            "word": 2
        }, 
        "https://wcs.starcraft2.com/en-us": {
            "used": 17, 
            "word": 2
        }, 
        "https://worldofwarcraft.com": {
            "used": 44, 
            "word": 1
        }
    }, 
    "apis": {
        "https://dev.battle.net": {
            "used": 4, 
            "word": 2
        }
    }, 
    "app": {
        "https://careers.blizzard.com": {
            "used": 8, 
            "word": 35
        }, 
        "https://dev.battle.net": {
            "used": 4, 
            "word": 1
        }, 
        "https://us.battle.net/account/download": {
            "used": 12, 
            "word": 3
        }, 
        "https://us.battle.net/support": {
            "used": 37, 
            "word": 1
        }, 
        "https://www.twitter.com/PlayOverwatch": {
            "used": 5, 
            "word": 4
        }
    }, 
    "appear": {
        "http://us.blizzard.com/company/about/privacy.html": {
            "used": 24, 
            "word": 1
        }
    }, 
    "applicable": {
        "http://us.blizzard.com/company/about/privacy.html": {
            "used": 24, 
            "word": 3
        }, 
        "https://careers.blizzard.com": {
            "used": 9, 
            "word": 1
        }
    }, 
    "applicants": {
        "https://careers.blizzard.com": {
            "used": 9, 
            "word": 1
        }
    }, 
    "apply": {
        "http://us.blizzard.com/company/about/privacy.html": {
            "used": 24, 
            "word": 3
        }, 
        "https://us.heroesofthestorm.com/esports/en-us": {
            "used": 13, 
            "word": 5
        }
    }, 
    "approaches": {
        "https://us.battle.net/sc2": {
            "used": 27, 
            "word": 1
        }
    }, 
    "appropriate": {
        "http://us.blizzard.com/company/about/privacy.html": {
            "used": 24, 
            "word": 1
        }
    }, 
    "approval": {
        "http://us.blizzard.com/company/about/privacy.html": {
            "used": 24, 
            "word": 1
        }
    }, 
    "apptit": {
        "https://www.youtube.com/watch": {
            "used": 12, 
            "word": 1
        }
    }, 
    "apr": {
        "https://www.twitter.com/PlayOverwatch": {
            "used": 5, 
            "word": 11
        }
    }, 
    "april": {
        "http://blizz.ly/OWC2017": {
            "used": 2, 
            "word": 1
        }, 
        "http://blizzard.com": {
            "used": 34, 
            "word": 3
        }, 
        "https://playoverwatch.com/en-us/worldcup": {
            "used": 23, 
            "word": 1
        }, 
        "https://us.battle.net/d3": {
            "used": 27, 
            "word": 4
        }, 
        "https://us.battle.net/heroes": {
            "used": 12, 
            "word": 3
        }, 
        "https://us.battle.net/sc2": {
            "used": 27, 
            "word": 2
        }
    }, 
    "aq": {
        "https://us.heroesofthestorm.com/esports/en-us": {
            "used": 13, 
            "word": 6
        }
    }, 
    "aqm": {
        "https://us.heroesofthestorm.com/esports/en-us": {
            "used": 13, 
            "word": 3
        }
    }, 
    "arcade": {
        "https://us.battle.net/sc2": {
            "used": 27, 
            "word": 2
        }
    }, 
    "archive": {
        "https://www.youtube.com/PlayOverwatch": {
            "used": 5, 
            "word": 2
        }
    }, 
    "archives": {
        "http://blizz.ly/OWU2017": {
            "used": 2, 
            "word": 2
        }, 
        "https://www.facebook.com/PlayOverwatch": {
            "used": 8, 
            "word": 1
        }, 
        "https://www.twitter.com/PlayOverwatch": {
            "used": 5, 
            "word": 1
        }, 
        "https://www.youtube.com/PlayOverwatch": {
            "used": 5, 
            "word": 1
        }
    }, 
    "area": {
        "http://us.blizzard.com/company/about/privacy.html": {
            "used": 24, 
            "word": 4
        }
    }, 
    "areas": {
        "http://us.blizzard.com/company/about/privacy.html": {
            "used": 24, 
            "word": 2
        }
    }, 
    "arena": {
        "https://blizzard.gamespress.com": {
            "used": 4, 
            "word": 1
        }, 
        "https://us.battle.net/hearthstone": {
            "used": 27, 
            "word": 1
        }
    }, 
    "argentina": {
        "http://blizz.ly/OWC2017": {
            "used": 2, 
            "word": 1
        }, 
        "https://blizzard.gamespress.com": {
            "used": 4, 
            "word": 1
        }, 
        "https://playoverwatch.com/en-us/worldcup": {
            "used": 23, 
            "word": 1
        }
    }, 
    "aria": {
        "https://careers.blizzard.com": {
            "used": 8, 
            "word": 1
        }, 
        "https://us.heroesofthestorm.com/esports/en-us": {
            "used": 13, 
            "word": 9
        }
    }, 
    "aring": {
        "https://us.heroesofthestorm.com/esports/en-us": {
            "used": 13, 
            "word": 2
        }
    }, 
    "armor": {
        "https://careers.blizzard.com": {
            "used": 9, 
            "word": 1
        }
    }, 
    "arriving": {
        "https://us.battle.net/sc2": {
            "used": 27, 
            "word": 1
        }
    }, 
    "arrow": {
        "https://careers.blizzard.com": {
            "used": 8, 
            "word": 3
        }, 
        "https://us.heroesofthestorm.com/esports/en-us": {
            "used": 13, 
            "word": 3
        }
    }, 
    "art": {
        "https://careers.blizzard.com": {
            "used": 9, 
            "word": 8
        }, 
        "https://www.twitter.com/PlayOverwatch": {
            "used": 5, 
            "word": 9
        }
    }, 
    "article": {
        "https://careers.blizzard.com": {
            "used": 9, 
            "word": 2
        }, 
        "https://us.heroesofthestorm.com/esports/en-us": {
            "used": 13, 
            "word": 33
        }
    }, 
    "articledescription": {
        "https://us.heroesofthestorm.com/esports/en-us": {
            "used": 13, 
            "word": 4
        }
    }, 
    "articleimage": {
        "https://us.heroesofthestorm.com/esports/en-us": {
            "used": 13, 
            "word": 8
        }
    }, 
    "articleimagewrapper": {
        "https://us.heroesofthestorm.com/esports/en-us": {
            "used": 13, 
            "word": 4
        }
    }, 
    "articles": {
        "https://us.heroesofthestorm.com/esports/en-us": {
            "used": 13, 
            "word": 1
        }
    }, 
    "articletextwrapper": {
        "https://us.heroesofthestorm.com/esports/en-us": {
            "used": 13, 
            "word": 4
        }
    }, 
    "articletitle": {
        "https://us.heroesofthestorm.com/esports/en-us": {
            "used": 13, 
            "word": 8
        }
    }, 
    "articletitlewrapper": {
        "https://us.heroesofthestorm.com/esports/en-us": {
            "used": 13, 
            "word": 4
        }
    }, 
    "artist": {
        "https://us.battle.net/d3": {
            "used": 27, 
            "word": 1
        }
    }, 
    "artwork": {
        "https://us.battle.net/hearthstone": {
            "used": 27, 
            "word": 3
        }, 
        "https://us.battle.net/hearthstone/en-us/esports": {
            "used": 16, 
            "word": 2
        }
    }, 
    "asia": {
        "http://blizz.ly/OWC2017": {
            "used": 2, 
            "word": 2
        }, 
        "http://blizz.ly/OWU2017": {
            "used": 2, 
            "word": 1
        }, 
        "http://blizzard.com": {
            "used": 34, 
            "word": 1
        }, 
        "http://us.blizzard.com/company/about/privacy.html": {
            "used": 24, 
            "word": 1
        }, 
        "https://battle.net/shop": {
            "used": 29, 
            "word": 1
        }, 
        "https://blizzard.gamespress.com": {
            "used": 4, 
            "word": 1
        }, 
        "https://overwatchleague.com/en-us": {
            "used": 29, 
            "word": 2
        }, 
        "https://playoverwatch.com": {
            "used": 38, 
            "word": 1
        }, 
        "https://playoverwatch.com/en-us": {
            "used": 0, 
            "word": 1
        }, 
        "https://playoverwatch.com/en-us/worldcup": {
            "used": 23, 
            "word": 2
        }, 
        "https://us.battle.net/account/download": {
            "used": 12, 
            "word": 1
        }, 
        "https://us.battle.net/feedback": {
            "used": 10, 
            "word": 1
        }, 
        "https://us.battle.net/forums": {
            "used": 18, 
            "word": 2
        }, 
        "https://us.battle.net/games/classic": {
            "used": 18, 
            "word": 1
        }, 
        "https://us.battle.net/hearthstone": {
            "used": 27, 
            "word": 2
        }, 
        "https://us.battle.net/hearthstone/en-us/esports": {
            "used": 16, 
            "word": 2
        }, 
        "https://us.battle.net/heroes": {
            "used": 12, 
            "word": 2
        }, 
        "https://us.battle.net/sc2": {
            "used": 27, 
            "word": 1
        }, 
        "https://us.battle.net/support": {
            "used": 37, 
            "word": 1
        }, 
        "https://wcs.starcraft2.com/en-us": {
            "used": 17, 
            "word": 2
        }
    }, 
    "ask": {
        "http://us.blizzard.com/company/about/privacy.html": {
            "used": 24, 
            "word": 3
        }, 
        "https://dev.battle.net": {
            "used": 4, 
            "word": 1
        }, 
        "https://www.facebook.com/PlayOverwatch": {
            "used": 8, 
            "word": 1
        }, 
        "https://www.twitter.com/PlayOverwatch": {
            "used": 5, 
            "word": 1
        }
    }, 
    "asked": {
        "http://us.blizzard.com/company/about/privacy.html": {
            "used": 24, 
            "word": 1
        }, 
        "https://us.battle.net/d3": {
            "used": 27, 
            "word": 1
        }
    }, 
    "aspx": {
        "http://us.blizzard.com/company/about/privacy.html": {
            "used": 24, 
            "word": 1
        }
    }, 
    "assassin": {
        "https://us.battle.net/heroes": {
            "used": 12, 
            "word": 6
        }
    }, 
    "assemble": {
        "https://overwatchleague.com/en-us": {
            "used": 29, 
            "word": 1
        }
    }, 
    "assent": {
        "http://us.blizzard.com/company/about/privacy.html": {
            "used": 24, 
            "word": 1
        }
    }, 
    "asset": {
        "http://us.blizzard.com/company/about/privacy.html": {
            "used": 24, 
            "word": 1
        }
    }, 
    "assigned": {
        "http://us.blizzard.com/company/about/privacy.html": {
            "used": 24, 
            "word": 1
        }
    }, 
    "associated": {
        "http://us.blizzard.com/company/about/privacy.html": {
            "used": 24, 
            "word": 2
        }, 
        "https://careers.blizzard.com": {
            "used": 9, 
            "word": 1
        }
    }, 
    "assure": {
        "http://us.blizzard.com/company/about/privacy.html": {
            "used": 24, 
            "word": 3
        }
    }, 
    "attachedblock": {
        "https://careers.blizzard.com": {
            "used": 8, 
            "word": 6
        }
    }, 
    "attack": {
        "https://www.facebook.com/PlayOverwatch": {
            "used": 8, 
            "word": 2
        }, 
        "https://www.twitter.com/PlayOverwatch": {
            "used": 5, 
            "word": 1
        }, 
        "https://www.youtube.com/watch": {
            "used": 12, 
            "word": 1
        }
    }, 
    "attention": {
        "http://us.blizzard.com/company/about/privacy.html": {
            "used": 24, 
            "word": 5
        }, 
        "https://www.youtube.com/watch": {
            "used": 12, 
            "word": 2
        }
    }, 
    "attn": {
        "http://us.blizzard.com/company/about/privacy.html": {
            "used": 24, 
            "word": 1
        }
    }, 
    "au": {
        "https://careers.blizzard.com": {
            "used": 8, 
            "word": 6
        }
    }, 
    "austin": {
        "https://us.battle.net/sc2": {
            "used": 27, 
            "word": 3
        }, 
        "https://wcs.starcraft2.com/en-us": {
            "used": 17, 
            "word": 8
        }
    }, 
    "australia": {
        "http://blizz.ly/OWC2017": {
            "used": 2, 
            "word": 1
        }, 
        "https://blizzard.gamespress.com": {
            "used": 4, 
            "word": 1
        }, 
        "https://playoverwatch.com/en-us/worldcup": {
            "used": 23, 
            "word": 1
        }
    }, 
    "austria": {
        "http://blizz.ly/OWC2017": {
            "used": 2, 
            "word": 1
        }, 
        "https://playoverwatch.com/en-us/worldcup": {
            "used": 23, 
            "word": 1
        }
    }, 
    "authenticated": {
        "https://dev.battle.net": {
            "used": 4, 
            "word": 1
        }
    }, 
    "authenticator": {
        "https://us.battle.net/account/download": {
            "used": 12, 
            "word": 1
        }
    }, 
    "authorized": {
        "https://us.battle.net/account/download": {
            "used": 12, 
            "word": 1
        }
    }, 
    "auto": {
        "https://careers.blizzard.com": {
            "used": 8, 
            "word": 5
        }
    }, 
    "automatically": {
        "http://us.blizzard.com/company/about/privacy.html": {
            "used": 24, 
            "word": 3
        }
    }, 
    "auxrn": {
        "https://us.heroesofthestorm.com/esports/en-us": {
            "used": 13, 
            "word": 3
        }
    }, 
    "available": {
        "http://blizz.ly/OWU2017": {
            "used": 2, 
            "word": 2
        }, 
        "http://blizzard.com": {
            "used": 34, 
            "word": 1
        }, 
        "http://us.blizzard.com/company/about/privacy.html": {
            "used": 24, 
            "word": 4
        }, 
        "https://us.battle.net/account/download": {
            "used": 12, 
            "word": 14
        }, 
        "https://us.battle.net/d3": {
            "used": 27, 
            "word": 1
        }, 
        "https://us.battle.net/games/classic": {
            "used": 18, 
            "word": 1
        }, 
        "https://us.battle.net/hearthstone": {
            "used": 27, 
            "word": 1
        }, 
        "https://us.battle.net/sc2": {
            "used": 27, 
            "word": 2
        }, 
        "https://wcs.starcraft2.com/en-us": {
            "used": 17, 
            "word": 1
        }
    }, 
    "ave": {
        "http://us.blizzard.com/company/about/privacy.html": {
            "used": 24, 
            "word": 22
        }
    }, 
    "avqxh": {
        "https://us.heroesofthestorm.com/esports/en-us": {
            "used": 13, 
            "word": 5
        }
    }, 
    "awaits": {
        "https://battle.net/shop": {
            "used": 29, 
            "word": 1
        }
    }, 
    "awards": {
        "http://us.blizzard.com/company/about/privacy.html": {
            "used": 24, 
            "word": 2
        }, 
        "https://careers.blizzard.com": {
            "used": 9, 
            "word": 1
        }
    }, 
    "aware": {
        "http://us.blizzard.com/company/about/privacy.html": {
            "used": 24, 
            "word": 4
        }
    }, 
    "away": {
        "http://blizz.ly/OWU2017": {
            "used": 2, 
            "word": 1
        }
    }, 
    "awe": {
        "https://us.battle.net/heroes": {
            "used": 12, 
            "word": 2
        }
    }, 
    "awesome": {
        "https://dev.battle.net": {
            "used": 4, 
            "word": 1
        }
    }, 
    "axis": {
        "https://www.twitter.com/PlayOverwatch": {
            "used": 5, 
            "word": 1
        }
    }
}